Topsis_HarshitaSingh_102003499/102003499.py
Topsis_HarshitaSingh_102003499-0.5.dist-info/LICENSE.txt
Topsis_HarshitaSingh_102003499-0.5.dist-info/METADATA
Topsis_HarshitaSingh_102003499-0.5.dist-info/WHEEL
Topsis_HarshitaSingh_102003499-0.5.dist-info/entry_points.txt
Topsis_HarshitaSingh_102003499-0.5.dist-info/top_level.txt
Topsis_HarshitaSingh_102003499-0.5.dist-info/RECORD
