Metadata-Version: 2.1
Name: Topsis-HarshitaSingh-102003499
Version: 0.5
Summary: Technique for Order Preference by Similarity to Ideal Solution (TOPSIS) originated in the 1980s as a multi-criteria decision making method. TOPSIS chooses the alternative of shortest Euclidean distance from the ideal solution, and greatest distance from the negative-ideal solution.
Home-page: UNKNOWN
Author: Harshita Singh
License: UNKNOWN
Platform: UNKNOWN
Requires-Dist: pandas
